wagtail_localize_ai/__init__.py
wagtail_localize_ai/apps.py
wagtail_localize_ai/default_settings.py
wagtail_localize_ai/models.py
wagtail_localize_ai/translator.py
wagtail_localize_ai/views.py
wagtail_localize_ai/wagtail_hooks.py
wagtail_localize_ai/locale/en/LC_MESSAGES/django.mo
wagtail_localize_ai/locale/en/LC_MESSAGES/django.po
wagtail_localize_ai/locale/it/LC_MESSAGES/django.mo
wagtail_localize_ai/locale/it/LC_MESSAGES/django.po
wagtail_localize_ai/migrations/0001_initial.py
wagtail_localize_ai/migrations/0002_alter_aitranslatorsettings_options_and_more.py
wagtail_localize_ai/migrations/0003_alter_aitranslatorsettings_prompt.py
wagtail_localize_ai/migrations/__init__.py
wagtail_localize_ai-0.2.0.dist-info/licenses/LICENSE
wagtail_localize_ai-0.2.0.dist-info/METADATA
wagtail_localize_ai-0.2.0.dist-info/WHEEL
wagtail_localize_ai-0.2.0.dist-info/top_level.txt
wagtail_localize_ai-0.2.0.dist-info/RECORD
