Metadata-Version: 2.4
Name: wagtail-localize-ai
Version: 0.2.0
Summary: LiteLLM powered machine translator for wagtail-localize
Author-email: Alessio Tognan <tognan@infofactory.it>
Requires-Python: >=3.9
License-File: LICENSE
Requires-Dist: litellm<2.0.0,>=1.63.2
Requires-Dist: wagtail-localize
Dynamic: license-file
